Imgscii-1.0.2.dist-info/DESCRIPTION.rst
Imgscii-1.0.2.dist-info/METADATA
Imgscii-1.0.2.dist-info/RECORD
Imgscii-1.0.2.dist-info/WHEEL
Imgscii-1.0.2.dist-info/metadata.json
Imgscii-1.0.2.dist-info/top_level.txt
imgscii/__init__.py
imgscii/imgscii.py
