Metadata-Version: 2.0
Name: Imgscii
Version: 1.0.2
Summary: Create ASCII artwork from images.
Home-page: https://github.com/campbellized/imgscii
Author: Chris Campbell
Author-email: campbellized@gmail.com
License: MIT
Requires-Dist: Pillow
Requires-Dist: colorama
